odoo8_addon_l10n_ar_account_payment-8.0.1.0.0.99.dev2-py2.7-nspkg.pth
odoo8_addon_l10n_ar_account_payment-8.0.1.0.0.99.dev2.dist-info/METADATA
odoo8_addon_l10n_ar_account_payment-8.0.1.0.0.99.dev2.dist-info/RECORD
odoo8_addon_l10n_ar_account_payment-8.0.1.0.0.99.dev2.dist-info/WHEEL
odoo8_addon_l10n_ar_account_payment-8.0.1.0.0.99.dev2.dist-info/namespace_packages.txt
odoo8_addon_l10n_ar_account_payment-8.0.1.0.0.99.dev2.dist-info/top_level.txt
odoo_addons/l10n_ar_account_payment/.gitignore
odoo_addons/l10n_ar_account_payment/AUTHORS
odoo_addons/l10n_ar_account_payment/__init__.py
odoo_addons/l10n_ar_account_payment/__openerp__.py
odoo_addons/l10n_ar_account_payment/account_voucher.py
odoo_addons/l10n_ar_account_payment/invoice.py
odoo_addons/l10n_ar_account_payment/payment_mode_receipt.py
odoo_addons/l10n_ar_account_payment/payment_mode_receipt_view.xml
odoo_addons/l10n_ar_account_payment/voucher_payment_receipt_view.xml
odoo_addons/l10n_ar_account_payment/i18n/es_AR.po
odoo_addons/l10n_ar_account_payment/i18n/l10n_ar_account_payment.po
odoo_addons/l10n_ar_account_payment/security/ir.model.access.csv
odoo_addons/l10n_ar_account_payment/static/description/icon.png
